ignite_rich_logger/__init__.py
ignite_rich_logger/__main__.py
ignite_rich_logger/handler.py
ignite_rich_logger-1.0.0.dist-info/LICENSE
ignite_rich_logger-1.0.0.dist-info/METADATA
ignite_rich_logger-1.0.0.dist-info/WHEEL
ignite_rich_logger-1.0.0.dist-info/top_level.txt
ignite_rich_logger-1.0.0.dist-info/RECORD
